{
  "UNK": "fd02",
  "id": 16,
  "total": 72,
  "ptrs": 304,
  "extra": 0,
  "ctrl_code": "20000000c2060000a6090000aa0900005c0c0000760c0000380f00009e120000fcffedfe01000200060004ff03ff0300c1ffffff1000bcff00f0ff0067ff0800fcfff9ff0800eefe00000500c1ff29001000ebfe000064ffffff0100",
  "contents": [
    {
      "magic": 65520,
      "id": 0,
      "speaker": "はかせ",
      "text": "さーて、まずは誰に話を聞こうかな？\n",
      "ctrl_code": "fbffc1ff2b001000ebfe000064ffffff0100"
    },
    {
      "magic": 65520,
      "id": 1,
      "speaker": "はかせ",
      "text": "誰に聞いても答えは一緒だと思うけど。\nぷぷぷ。阪本の驚く顔が楽しみ♪\n",
      "ctrl_code": "fbffedffc1ffffff1000c0ff030033001000ebfe000064ffffff0100"
    },
    {
      "magic": 65520,
      "id": 2,
      "speaker": "はかせ",
      "text": "あっ、おねえさん、ちょっといい？\n",
      "ctrl_code": "fbffc0ff04006a011000ebfe000064ffffff1800"
    },
    {
      "magic": 65520,
      "id": 3,
      "speaker": "みお姉",
      "text": "はい？　……わ〜、白衣着てる〜！\n可愛い〜。\n",
      "ctrl_code": "fbffc1ff2b001000ebfe000064ffffff0100"
    },
    {
      "magic": 65520,
      "id": 4,
      "speaker": "はかせ",
      "text": "…………！\n",
      "ctrl_code": "fbffc1ff69011000ebfe000064ffffff1800"
    },
    {
      "magic": 65520,
      "id": 5,
      "speaker": "みお姉",
      "text": "ねえねえ、なんで白衣着てるの？\n",
      "ctrl_code": "fbffc1ff33001000ebfe000064ffffff0100"
    },
    {
      "magic": 65520,
      "id": 6,
      "speaker": "はかせ",
      "text": "えへへ、それはね、\nはかせがはかせだからだよ。\n",
      "ctrl_code": "fbffc1ff6a011000ebfe000064ffffff1800"
    },
    {
      "magic": 65520,
      "id": 7,
      "speaker": "みお姉",
      "text": "博士なんだ〜。\nこんなに可愛いのに〜。\n",
      "ctrl_code": "fbffc1ff2b001000ebfe000064ffffff0100"
    },
    {
      "magic": 65520,
      "id": 8,
      "speaker": "はかせ",
      "text": "えへへへ。\nはかせ可愛い？\n",
      "ctrl_code": "fbffc1ff69011000ebfe000064ffffff1800"
    },
    {
      "magic": 65520,
      "id": 9,
      "speaker": "みお姉",
      "text": "可愛い〜。\nこのまま連れてっちゃいたいくらい♪\n",
      "ctrl_code": "fbffc1ff33001000ebfe000064ffffff0100"
    },
    {
      "magic": 65520,
      "id": 10,
      "speaker": "はかせ",
      "text": "えへへへ。\nはかせ、連れてかれちゃう。\n",
      "ctrl_code": "fbffc1ff31001000ebfe0000adffffff64ffffff0100"
    },
    {
      "magic": 65520,
      "id": 11,
      "speaker": "はかせ",
      "text": "……………。\n",
      "ctrl_code": "fbff67ffffff66ff7b000000e8fe0300c1ff30001000ebfe0100adffffff64ffffff0100"
    },
    {
      "magic": 65520,
      "id": 12,
      "speaker": "はかせ",
      "text": "（あっ！？　はかせ誘拐されちゃう！）\n",
      "ctrl_code": "98ff0000effe030097fffbff67ff0e00c1ff2a001000ebfe0100adffffff64ffffff0100"
    },
    {
      "magic": 65520,
      "id": 13,
      "speaker": "はかせ",
      "text": "（この人、悪い人かも……\n　早く逃げないと……）\n",
      "ctrl_code": "fbffc1ff6a011000ebfe000064ffffff1800"
    },
    {
      "magic": 65520,
      "id": 14,
      "speaker": "みお姉",
      "text": "ねえねえ、はかせはここで何してるの？\n何かの研究なの？\n",
      "ctrl_code": "fbffc1ff33001000ebfe000064ffffff0100"
    },
    {
      "magic": 65520,
      "id": 15,
      "speaker": "はかせ",
      "text": "えっ？　あ、そうだ。\nおねえさん、ネジは可愛いよね？\n",
      "ctrl_code": "fbffc1ff69011000ebfe000064ffffff1800"
    },
    {
      "magic": 65520,
      "id": 16,
      "speaker": "みお姉",
      "text": "ネジ？\n",
      "ctrl_code": "fbffc1ff2b001000ebfe000064ffffff0100"
    },
    {
      "magic": 65520,
      "id": 17,
      "speaker": "はかせ",
      "text": "そう、ネジ！\n可愛いよね！\n",
      "ctrl_code": "fbffc1ff69011000ebfe0000adffffff64ffffff1800"
    },
    {
      "magic": 65520,
      "id": 18,
      "speaker": "みお姉",
      "text": "……………。\n",
      "ctrl_code": "fbffc1ff6a011000ebfe000064ffffff1800"
    },
    {
      "magic": 65520,
      "id": 19,
      "speaker": "みお姉",
      "text": "あ〜。なのちゃんのこと？\n",
      "ctrl_code": "fbffc1ff31001000ebfe000064ffffff0100"
    },
    {
      "magic": 65520,
      "id": 20,
      "speaker": "はかせ",
      "text": "えっ！？　なののこと知ってるの！？\n",
      "ctrl_code": "fbffc1ff6a011000ebfe000064ffffff1800"
    },
    {
      "magic": 65520,
      "id": 21,
      "speaker": "みお姉",
      "text": "うん、知ってる知ってる。\nあのネジ可愛いよね〜。\n",
      "ctrl_code": "fbff67ffffffc1ff37001000ebfe000064ffffff0100"
    },
    {
      "magic": 65520,
      "id": 22,
      "speaker": "はかせ",
      "text": "……………！\n",
      "ctrl_code": "fbff67ff0800c1ff33001000ebfe0100adffffff64ffffff0100"
    },
    {
      "magic": 65520,
      "id": 23,
      "speaker": "はかせ",
      "text": "（このおねえさんはいい人だ！！）\n",
      "ctrl_code": "fbfffefe020001007fff0200edffc1ffffff1000c1ff26011000ebfe000064ffffff0d00"
    },
    {
      "magic": 65520,
      "id": 24,
      "speaker": "阪本さん",
      "text": "それは無いだろ……。\n",
      "ctrl_code": "fbffedffc8ff260129001000ebfe000064ffffff0100"
    },
    {
      "magic": 65520,
      "id": 25,
      "speaker": "はかせ",
      "text": "あっ、阪本！\n",
      "ctrl_code": "fbffc0ff040069011000ebfe000064ffffff1800"
    },
    {
      "magic": 65520,
      "id": 26,
      "speaker": "みお姉",
      "text": "えっ？　この猫喋るの！？\n",
      "ctrl_code": "fbffebfe000064ffffff0100"
    },
    {
      "magic": 65520,
      "id": 27,
      "speaker": "はかせ",
      "text": "うん！　喋れるんだよ。\n",
      "ctrl_code": "fbffc1ff6a011000ebfe000064ffffff1800"
    },
    {
      "magic": 65520,
      "id": 28,
      "speaker": "みお姉",
      "text": "すごいすごーーーい！！\n",
      "ctrl_code": "fbffedfffcfffaff01000000f8ff0800ecfec1ffffff100067fffffff4ff1e00f2fef0febcffdb01100067ff0f00faff01000000f9ff0800e8fe0200c1ffba011000ebfe000065ff00002200"
    },
    {
      "magic": 65520,
      "id": 29,
      "speaker": "[{FF07}]",
      "text": "うわ、やめろ！\nそんなに撫でるんじゃない！\n",
      "ctrl_code": "fbffc1ffbe011000ebfe000065ff01002300"
    },
    {
      "magic": 65520,
      "id": 30,
      "speaker": "[{FF08}]",
      "text": "まあまあ。\n猫なんだし撫でられても仕方ないだろ。\n",
      "ctrl_code": "fbffc1ffb4011000ebfe000065ff02002200"
    },
    {
      "magic": 65520,
      "id": 31,
      "speaker": "[{FF07}]",
      "text": "そうじゃなくて！\n頭を撫でたりなんかしたら……。\n",
      "ctrl_code": "fbff66ff0b000000c1ffbf011000ebfe000065ff03002300"
    },
    {
      "magic": 65520,
      "id": 32,
      "speaker": "[{FF08}]",
      "text": "ええっ！？\n",
      "ctrl_code": "fbffedffaaff0200ff0063ff0000c1ffffffff00fdfefcfeadffffffe8fe0200ebfe000065ff04002200"
    },
    {
      "magic": 65520,
      "id": 33,
      "speaker": "[{FF07}]",
      "text": "だからやめろと言ったのにー！\n",
      "ctrl_code": "fbffedfffcfff5ff040067ffffff63ffffffaaff00000000fdfebdffffff1000c1ffffff1000c2ffffff1000bcff6201ff00dafff6ff0800eafee9fef7ff0800fcffffff7fff030066ffc4000000c1ff2f001000ebfe000064ffffff0100"
    },
    {
      "magic": 65520,
      "id": 34,
      "speaker": "はかせ",
      "text": "あっ……。\n",
      "ctrl_code": "fbff05ffc1ff6a011000ebfe000064ffffff1800"
    },
    {
      "magic": 65520,
      "id": 35,
      "speaker": "みお姉",
      "text": "あははははは。お腹減ったんだ。\nもうお昼だもんね。\n",
      "ctrl_code": "fbffc1ff2e001000ebfe000064ffffff0100"
    },
    {
      "magic": 65520,
      "id": 36,
      "speaker": "はかせ",
      "text": "うん……はかせお腹すいた……。\n",
      "ctrl_code": "fbffc1ff69011000ebfe000064ffffff1800"
    },
    {
      "magic": 65520,
      "id": 37,
      "speaker": "みお姉",
      "text": "じゃあ大工カフェにでも行く？\n一緒にご飯食べようよ。\n",
      "ctrl_code": "fbffc1ff29001000ebfe000064ffffff0100"
    },
    {
      "magic": 65520,
      "id": 38,
      "speaker": "はかせ",
      "text": "でもはかせお金持ってないから……。\n",
      "ctrl_code": "fbffc1ff6a011000ebfe000064ffffff1800"
    },
    {
      "magic": 65520,
      "id": 39,
      "speaker": "みお姉",
      "text": "それくらい私が[{0D88}]ってあげるよ。\nだから行こう行こう♪\n",
      "ctrl_code": "fbffc1ff33001000ebfe0100adffffff64ffffff0100"
    },
    {
      "magic": 65520,
      "id": 40,
      "speaker": "はかせ",
      "text": "（やっぱりこのおねえさんはいい人だ！！）\n",
      "ctrl_code": "fbffc1ff2e001000ebfe0100adffffff64ffffff0100"
    },
    {
      "magic": 65520,
      "id": 41,
      "speaker": "はかせ",
      "text": "（あっ、でも前になのが知らない人に\n　ついていっちゃダメって……）\n",
      "ctrl_code": "fbffc1ff69011000ebfe000064ffffff1800"
    },
    {
      "magic": 65520,
      "id": 42,
      "speaker": "みお姉",
      "text": "ん？　どうしたの？\n何か他に食べたい物があるの？\n",
      "ctrl_code": "fdff7fff040002ff01ff0000960005003200fbfffa0000fffffe050006000700c1ff33001000ebfe000065ff05000100"
    },
    {
      "magic": 65520,
      "id": 43,
      "speaker": "はかせ",
      "text": "オムライスが食べたい！\n",
      "ctrl_code": "fbffeefe0e000400c1ff6a011000ebfe000065ff06001800"
    },
    {
      "magic": 65520,
      "id": 44,
      "speaker": "みお姉",
      "text": "オムライスが好きなんだ。\nじゃあ別のところに行こうか。\n",
      "ctrl_code": "fbffc1ff2b001000ebfe000065ff07000100"
    },
    {
      "magic": 65520,
      "id": 45,
      "speaker": "はかせ",
      "text": "行こーー！\n",
      "ctrl_code": "fbffc1ff69011000ebfe000065ff08001800"
    },
    {
      "magic": 65520,
      "id": 46,
      "speaker": "みお姉",
      "text": "じゃあオムライスの後に\n大工カフェでお茶しようか。\n",
      "ctrl_code": "fbffc1ff33001000ebfe000065ff09000100"
    },
    {
      "magic": 65520,
      "id": 47,
      "speaker": "はかせ",
      "text": "しよーー！\n",
      "ctrl_code": "fbffc1ff6a011000ebfe000065ff0a001800"
    },
    {
      "magic": 65520,
      "id": 48,
      "speaker": "みお姉",
      "text": "あははは、可愛いー。\n本当に連れてっちゃいたいなー♪\n",
      "ctrl_code": "fbffc1ff2b001000ebfe000065ff0b000100"
    },
    {
      "magic": 65520,
      "id": 49,
      "speaker": "はかせ",
      "text": "えへへへ。\nはかせ今度こそ連れてかれちゃう。\n",
      "ctrl_code": "fbffc1ff2d001000ebfe0000adffffff65ff0c000100"
    },
    {
      "magic": 65520,
      "id": 50,
      "speaker": "はかせ",
      "text": "……………。\n",
      "ctrl_code": "fbfff8ff0800daff90ffffffdeff0000003003000100ffff67ffffffdbff000063ffffff66ffffff0000daffbcffed01ff00c1fffeffff0090ffffff90ffffff90ffffff67ffffff71ff000063ffffff90ffffffedfff9ff0800e8fe030066ff7c000000ebfe0100adffffff65ff0d000100"
    },
    {
      "magic": 65520,
      "id": 51,
      "speaker": "はかせ",
      "text": "（誘拐されちゃう！！）\n",
      "ctrl_code": "98ff0000effe030097fffdff67ffffffe7fe0000fdff67ffffffeafee9fef7ff0800fcffffffc1ff2e001000ebfe000065ff0e000100"
    },
    {
      "magic": 65520,
      "id": 52,
      "speaker": "はかせ",
      "text": "えっとね、はかせ、なのに知らない人に\nついていっちゃダメって言われてるから……。\n",
      "ctrl_code": "fbffc1ff6a011000ebfe000065ff0f001800"
    },
    {
      "magic": 65520,
      "id": 53,
      "speaker": "みお姉",
      "text": "うんうん、\n知らない人について行っちゃダメだぞ？\n",
      "ctrl_code": "fbffc1ff2c001000ebfe000065ff10000100"
    },
    {
      "magic": 65520,
      "id": 54,
      "speaker": "はかせ",
      "text": "うん……だからおねえさんに\nついていくことはできないの。\n",
      "ctrl_code": "fbffc1ff69011000ebfe000065ff11001800"
    },
    {
      "magic": 65520,
      "id": 55,
      "speaker": "みお姉",
      "text": "でも、私はなのちゃんを知ってるよ？\n",
      "ctrl_code": "fbffc1ff33001000ebfe000065ff12000100"
    },
    {
      "magic": 65520,
      "id": 56,
      "speaker": "はかせ",
      "text": "…………！！\n",
      "ctrl_code": "fbffc1ff6a011000ebfe000065ff13001800"
    },
    {
      "magic": 65520,
      "id": 57,
      "speaker": "みお姉",
      "text": "だから私は知らない人じゃなくて\nなのちゃんが知ってる人だよ。\n",
      "ctrl_code": "fbffe8fe0200c1ff2b001000ebfe000065ff14000100"
    },
    {
      "magic": 65520,
      "id": 58,
      "speaker": "はかせ",
      "text": "そっか！　知らない人じゃない！\n",
      "ctrl_code": "98ff0000eefe0e000400effe070097fffbffc1ff69011000ebfe000065ff15001800"
    },
    {
      "magic": 65520,
      "id": 59,
      "speaker": "みお姉",
      "text": "だからついていっても大丈夫だよ。\n",
      "ctrl_code": "fbffc1ff33001000ebfe000065ff16000100"
    },
    {
      "magic": 65520,
      "id": 60,
      "speaker": "はかせ",
      "text": "ついていく！\n",
      "ctrl_code": "fbfff8ff0800daff73ff0000deff0000003003000100ffff67ffffffdbff000063ffffff66ffffff0000daffbcffea01ff00c1fffeffff0090ffffff90ffffff90ffffff67fffcff71ff000063ffffff90ffffffedfff9ff0800ebfe000065ff17001800"
    },
    {
      "magic": 65520,
      "id": 61,
      "speaker": "みお姉",
      "text": "それじゃあ行こっか♪\n",
      "ctrl_code": "fbffebfe000065ff18000100"
    },
    {
      "magic": 65520,
      "id": 62,
      "speaker": "はかせ",
      "text": "行こーー！！\n",
      "ctrl_code": "fdff67ffffffe7fe0000fdff67ffffffeafee9fef7ff0800fcffffffc1ff2d001000ebfe0100adffffff65ff19000100"
    },
    {
      "magic": 65520,
      "id": 63,
      "speaker": "はかせ",
      "text": "（ついていったらなのに怒られちゃうから\n　断らないと）\n",
      "ctrl_code": "fbffc1ff2f001000ebfe000065ff1a000100"
    },
    {
      "magic": 65520,
      "id": 64,
      "speaker": "はかせ",
      "text": "あのね、はかせはおうちにご飯があるから\nそっちを食べないといけないの。\n",
      "ctrl_code": "fbffc1ff69011000ebfe000065ff1b001800"
    },
    {
      "magic": 65520,
      "id": 65,
      "speaker": "みお姉",
      "text": "そうなの？\nじゃあ軽く食べるだけにしようか。\n",
      "ctrl_code": "fbffc1ff33001000ebfe000065ff1c000100"
    },
    {
      "magic": 65520,
      "id": 66,
      "speaker": "はかせ",
      "text": "うん！\n",
      "ctrl_code": "fbffc1ff2f001000ebfe0100adffffff65ff1d000100"
    },
    {
      "magic": 65520,
      "id": 67,
      "speaker": "はかせ",
      "text": "（……あれ？）\n",
      "ctrl_code": "98ff0000effe020097fffbffeefe1500040067ff1000c1ff2e001000ebfe000065ff1e000100"
    },
    {
      "magic": 65520,
      "id": 68,
      "speaker": "はかせ",
      "text": "あ、あのね、でもね、会ったばかりなのに\nごちそうしてもらうのは悪いから……。\n",
      "ctrl_code": "fbffc1ff6a011000ebfe000065ff1f001800"
    },
    {
      "magic": 65520,
      "id": 69,
      "speaker": "みお姉",
      "text": "大丈夫。バイト代入ったばかりだから。\n",
      "ctrl_code": "fbffc1ff33001000ebfe000065ff20000100"
    },
    {
      "magic": 65520,
      "id": 70,
      "speaker": "はかせ",
      "text": "そっか！　じゃあ行こー！\n",
      "ctrl_code": "fbfff8ff0800daff73ff0000deff0000003003000100ffff67ffffffdbff000063ffffff66ffffff0000daffbcffea01ff00c1fffeffff0090ffffff90ffffff90ffffff67fffcff71ff000063ffffff90ffffffedfff9ff0800ebfe0100adffffff65ff21000100"
    },
    {
      "magic": 65520,
      "id": 71,
      "speaker": "はかせ",
      "text": "（あれー！？）\n",
      "ctrl_code": "98ff0000effe030097fffdff67ffffffe7fe0000fdff67ffffffeafee9fef7ff0800fcffffff"
    }
  ]
}